Workbook
Name CH_APP: '4. Vue globale MB mensuels '!$B$5
Name P_V: '4. Vue globale MB mensuels '!$B$19

Sheet 1. Calcul de Marge Brute
A1: Tableau de la croissance financière de votre projet: en prévisionnel et en réel, sur 18 mois (durée du test)
A3: INSTRUCTION:
A4: Copier dans "Liste produits-services" du Plan Financier les listes de produits et services à coller ici.
A5: Idem pour les PV (Prix de Vente) tvaC et pour les frais d'approvisionnement Htva.
A6: Tout changement que vous appliquez ici est à appliquer dans le Plan Financier
A8: Liste produits-services | C8: PV tvaC | D8: PV tvaC | E8: PV tvaC | G8: PV Htva | H8: PV Htva | I8: PV Htva
C9: 0.21 | D9: 0.12 | E9: 0.06 | G9: 0.21 | H9: 0.12 | I9: 0.06 | J9: Frais appro Vtva | K9: Marge Brute Htva | L9: << Marge brute Htva = PV Htva - Frais d'approvisionnement Htva
A10: Site web ASBL (forfait site + formation + 3 mois support) | C10: 2000 | G10: =C10/(1+C$9) | H10: =D10/(1+D$9) | I10: =E10/(1+E$9) | J10: 0 | K10: =SUM(G10:I10)-J10
A11: Hébergement + nom de domaine (forfait annuel / site du parc) | C11: 120 | G11: =C11/(1+C$9) | H11: =D11/(1+D$9) | I11: =E11/(1+E$9) | J11: 0 | K11: =SUM(G11:I11)-J11
A12: App / outil de gestion sur mesure (CRM, subsides, inscriptions) | C12: 5000 | G12: =C12/(1+C$9) | H12: =D12/(1+D$9) | I12: =E12/(1+E$9) | J12: 0 | K12: =SUM(G12:I12)-J12
A13: Hébergement app de gestion (forfait annuel / app) | C13: 180 | G13: =C13/(1+C$9) | H13: =D13/(1+D$9) | I13: =E13/(1+E$9) | J13: 0 | K13: =SUM(G13:I13)-J13
G14: =C14/(1+C$9) | H14: =D14/(1+D$9) | I14: =E14/(1+E$9) | K14: =SUM(G14:I14)-J14
G15: =C15/(1+C$9) | H15: =D15/(1+D$9) | I15: =E15/(1+E$9) | K15: =SUM(G15:I15)-J15
G16: =C16/(1+C$9) | H16: =D16/(1+D$9) | I16: =E16/(1+E$9) | K16: =SUM(G16:I16)-J16
G17: =C17/(1+C$9) | H17: =D17/(1+D$9) | I17: =E17/(1+E$9) | K17: =SUM(G17:I17)-J17
G18: =C18/(1+C$9) | H18: =D18/(1+D$9) | I18: =E18/(1+E$9) | K18: =SUM(G18:I18)-J18
G19: =C19/(1+C$9) | H19: =D19/(1+D$9) | I19: =E19/(1+E$9) | K19: =SUM(G19:I19)-J19
G20: =C20/(1+C$9) | H20: =D20/(1+D$9) | I20: =E20/(1+E$9) | K20: =SUM(G20:I20)-J20
G21: =C21/(1+C$9) | H21: =D21/(1+D$9) | I21: =E21/(1+E$9) | K21: =SUM(G21:I21)-J21
G22: =C22/(1+C$9) | H22: =D22/(1+D$9) | I22: =E22/(1+E$9) | K22: =SUM(G22:I22)-J22

Sheet 2. Détail prévisionnel ventes  
A1: Prévisionnel | B1: Nom : | C1: Oliver Van Droogenbroeck
C3: 46266 | E3: 46296 | G3: 46327 | I3: 46357 | K3: 46388 | M3: 46419 | O3: 46447 | Q3: 46478 | S3: 46508 | U3: 46539 | W3: 46569 | Y3: 46600 | AA3: 46631 | AC3: 46661 | AE3: 46692 | AG3: 46722 | AI3: 46753 | AK3: 46784
A4: TYPE DE PRESTATION | B4: Marge Brute Unitaire | C4: 1 | E4: 2 | G4: 3 | I4: 4 | K4: 5 | M4: 6 | O4: 7 | Q4: 8 | S4: 9 | U4: 10 | W4: 11 | Y4: 12 | AA4: 13 | AC4: 14 | AE4: 15 | AG4: 16 | AI4: 17 | AK4: 18
B5: HTVA | C5: Nbre | D5: Tot. | E5: Nbre | F5: Tot. | G5: Nbre | H5: Tot. | I5: Nbre | J5: Tot. | K5: Nbre | L5: Tot. | M5: Nbre | N5: Tot. | O5: Nbre | P5: Tot. | Q5: Nbre | R5: Tot. | S5: Nbre | T5: Tot. | U5: Nbre | V5: Tot. | W5: Nbre | X5: Tot. | Y5: Nbre | Z5: Tot. | AA5: Nbre | AB5: Tot. | AC5: Nbre | AD5: Tot. | AE5: Nbre | AF5: Tot. | AG5: Nbre | AH5: Tot. | AI5: Nbre | AJ5: Tot. | AK5: Nbre | AL5: Tot.
A6: ='1. Calcul de Marge Brute'!A10 | B6: ='1. Calcul de Marge Brute'!K10 | C6: 1 | D6: =C6*$B6 | E6: 1 | F6: =E6*$B6 | G6: 1 | H6: =G6*$B6 | I6: 1 | J6: =I6*$B6 | K6: 1 | L6: =K6*$B6 | M6: 1 | N6: =M6*$B6 | O6: 2 | P6: =O6*$B6 | Q6: 1 | R6: =Q6*$B6 | S6: 1 | T6: =S6*$B6 | U6: 2 | V6: =U6*$B6 | W6: 1 | X6: =W6*$B6 | Y6: 1 | Z6: =Y6*$B6 | AA6: 0 | AB6: =AA6*$B6 | AC6: 1 | AD6: =AC6*$B6 | AE6: 1 | AF6: =AE6*$B6 | AG6: 1 | AH6: =AG6*$B6 | AI6: 0 | AJ6: =AI6*$B6 | AK6: 1 | AL6: =AK6*$B6
A7: ='1. Calcul de Marge Brute'!A11 | B7: ='1. Calcul de Marge Brute'!K11 | C7: 1 | D7: =C7*$B7 | E7: 1 | F7: =E7*$B7 | G7: 1 | H7: =G7*$B7 | I7: 1 | J7: =I7*$B7 | K7: 1 | L7: =K7*$B7 | M7: 1 | N7: =M7*$B7 | O7: 2 | P7: =O7*$B7 | Q7: 1 | R7: =Q7*$B7 | S7: 1 | T7: =S7*$B7 | U7: 2 | V7: =U7*$B7 | W7: 1 | X7: =W7*$B7 | Y7: 1 | Z7: =Y7*$B7 | AA7: 0 | AB7: =AA7*$B7 | AC7: 1 | AD7: =AC7*$B7 | AE7: 1 | AF7: =AE7*$B7 | AG7: 1 | AH7: =AG7*$B7 | AI7: 0 | AJ7: =AI7*$B7 | AK7: 1 | AL7: =AK7*$B7
A8: ='1. Calcul de Marge Brute'!A12 | B8: ='1. Calcul de Marge Brute'!K12 | C8: 0 | D8: =C8*$B8 | E8: 0 | F8: =E8*$B8 | G8: 0 | H8: =G8*$B8 | I8: 0 | J8: =I8*$B8 | K8: 0 | L8: =K8*$B8 | M8: 1 | N8: =M8*$B8 | O8: 0 | P8: =O8*$B8 | Q8: 0 | R8: =Q8*$B8 | S8: 0 | T8: =S8*$B8 | U8: 0 | V8: =U8*$B8 | W8: 1 | X8: =W8*$B8 | Y8: 0 | Z8: =Y8*$B8 | AA8: 0 | AB8: =AA8*$B8 | AC8: 0 | AD8: =AC8*$B8 | AE8: 0 | AF8: =AE8*$B8 | AG8: 0 | AH8: =AG8*$B8 | AI8: 1 | AJ8: =AI8*$B8 | AK8: 0 | AL8: =AK8*$B8
A9: ='1. Calcul de Marge Brute'!A13 | B9: ='1. Calcul de Marge Brute'!K13 | C9: 0 | D9: =C9*$B9 | E9: 0 | F9: =E9*$B9 | G9: 0 | H9: =G9*$B9 | I9: 0 | J9: =I9*$B9 | K9: 0 | L9: =K9*$B9 | M9: 1 | N9: =M9*$B9 | O9: 0 | P9: =O9*$B9 | Q9: 0 | R9: =Q9*$B9 | S9: 0 | T9: =S9*$B9 | U9: 0 | V9: =U9*$B9 | W9: 1 | X9: =W9*$B9 | Y9: 0 | Z9: =Y9*$B9 | AA9: 0 | AB9: =AA9*$B9 | AC9: 0 | AD9: =AC9*$B9 | AE9: 0 | AF9: =AE9*$B9 | AG9: 0 | AH9: =AG9*$B9 | AI9: 1 | AJ9: =AI9*$B9 | AK9: 0 | AL9: =AK9*$B9
A10: ='1. Calcul de Marge Brute'!A14 | B10: ='1. Calcul de Marge Brute'!K14 | D10: =C10*$B10 | F10: =E10*$B10 | H10: =G10*$B10 | J10: =I10*$B10 | L10: =K10*$B10 | N10: =M10*$B10 | P10: =O10*$B10 | R10: =Q10*$B10 | T10: =S10*$B10 | V10: =U10*$B10 | X10: =W10*$B10 | Z10: =Y10*$B10 | AB10: =AA10*$B10 | AD10: =AC10*$B10 | AF10: =AE10*$B10 | AH10: =AG10*$B10 | AJ10: =AI10*$B10 | AL10: =AK10*$B10
A11: ='1. Calcul de Marge Brute'!A15 | B11: ='1. Calcul de Marge Brute'!K15 | D11: =C11*$B11 | F11: =E11*$B11 | H11: =G11*$B11 | J11: =I11*$B11 | L11: =K11*$B11 | N11: =M11*$B11 | P11: =O11*$B11 | R11: =Q11*$B11 | T11: =S11*$B11 | V11: =U11*$B11 | X11: =W11*$B11 | Z11: =Y11*$B11 | AB11: =AA11*$B11 | AD11: =AC11*$B11 | AF11: =AE11*$B11 | AH11: =AG11*$B11 | AJ11: =AI11*$B11 | AL11: =AK11*$B11
A12: ='1. Calcul de Marge Brute'!A16 | B12: ='1. Calcul de Marge Brute'!K16 | D12: =C12*$B12 | F12: =E12*$B12 | H12: =G12*$B12 | J12: =I12*$B12 | L12: =K12*$B12 | N12: =M12*$B12 | P12: =O12*$B12 | R12: =Q12*$B12 | T12: =S12*$B12 | V12: =U12*$B12 | X12: =W12*$B12 | Z12: =Y12*$B12 | AB12: =AA12*$B12 | AD12: =AC12*$B12 | AF12: =AE12*$B12 | AH12: =AG12*$B12 | AJ12: =AI12*$B12 | AL12: =AK12*$B12
A13: ='1. Calcul de Marge Brute'!A17 | B13: ='1. Calcul de Marge Brute'!K17 | D13: =C13*$B13 | F13: =E13*$B13 | H13: =G13*$B13 | J13: =I13*$B13 | L13: =K13*$B13 | N13: =M13*$B13 | P13: =O13*$B13 | R13: =Q13*$B13 | T13: =S13*$B13 | V13: =U13*$B13 | X13: =W13*$B13 | Z13: =Y13*$B13 | AB13: =AA13*$B13 | AD13: =AC13*$B13 | AF13: =AE13*$B13 | AH13: =AG13*$B13 | AJ13: =AI13*$B13 | AL13: =AK13*$B13
A14: ='1. Calcul de Marge Brute'!A18 | B14: ='1. Calcul de Marge Brute'!K18 | D14: =C14*$B14 | F14: =E14*$B14 | H14: =G14*$B14 | J14: =I14*$B14 | L14: =K14*$B14 | N14: =M14*$B14 | P14: =O14*$B14 | R14: =Q14*$B14 | T14: =S14*$B14 | V14: =U14*$B14 | X14: =W14*$B14 | Z14: =Y14*$B14 | AB14: =AA14*$B14 | AD14: =AC14*$B14 | AF14: =AE14*$B14 | AH14: =AG14*$B14 | AJ14: =AI14*$B14 | AL14: =AK14*$B14
A15: ='1. Calcul de Marge Brute'!A19 | B15: ='1. Calcul de Marge Brute'!K19 | D15: =C15*$B15 | F15: =E15*$B15 | H15: =G15*$B15 | J15: =I15*$B15 | L15: =K15*$B15 | N15: =M15*$B15 | P15: =O15*$B15 | R15: =Q15*$B15 | T15: =S15*$B15 | V15: =U15*$B15 | X15: =W15*$B15 | Z15: =Y15*$B15 | AB15: =AA15*$B15 | AD15: =AC15*$B15 | AF15: =AE15*$B15 | AH15: =AG15*$B15 | AJ15: =AI15*$B15 | AL15: =AK15*$B15
A16: ='1. Calcul de Marge Brute'!A20 | B16: ='1. Calcul de Marge Brute'!K20 | D16: =C16*$B16 | F16: =E16*$B16 | H16: =G16*$B16 | J16: =I16*$B16 | L16: =K16*$B16 | N16: =M16*$B16 | P16: =O16*$B16 | R16: =Q16*$B16 | T16: =S16*$B16 | V16: =U16*$B16 | X16: =W16*$B16 | Z16: =Y16*$B16 | AB16: =AA16*$B16 | AD16: =AC16*$B16 | AF16: =AE16*$B16 | AH16: =AG16*$B16 | AJ16: =AI16*$B16 | AL16: =AK16*$B16
A17: ='1. Calcul de Marge Brute'!A21 | B17: ='1. Calcul de Marge Brute'!K21 | D17: =C17*$B17 | F17: =E17*$B17 | H17: =G17*$B17 | J17: =I17*$B17 | L17: =K17*$B17 | N17: =M17*$B17 | P17: =O17*$B17 | R17: =Q17*$B17 | T17: =S17*$B17 | V17: =U17*$B17 | X17: =W17*$B17 | Z17: =Y17*$B17 | AB17: =AA17*$B17 | AD17: =AC17*$B17 | AF17: =AE17*$B17 | AH17: =AG17*$B17 | AJ17: =AI17*$B17 | AL17: =AK17*$B17
A18: ='1. Calcul de Marge Brute'!A22 | B18: ='1. Calcul de Marge Brute'!K22 | D18: =C18*$B18 | F18: =E18*$B18 | H18: =G18*$B18 | J18: =I18*$B18 | L18: =K18*$B18 | N18: =M18*$B18 | P18: =O18*$B18 | R18: =Q18*$B18 | T18: =S18*$B18 | V18: =U18*$B18 | X18: =W18*$B18 | Z18: =Y18*$B18 | AB18: =AA18*$B18 | AD18: =AC18*$B18 | AF18: =AE18*$B18 | AH18: =AG18*$B18 | AJ18: =AI18*$B18 | AL18: =AK18*$B18
A20: TOTAUX | D20: =SUM(D6:D19) | F20: =SUM(F6:F19) | H20: =SUM(H6:H19) | J20: =SUM(J6:J19) | L20: =SUM(L6:L19) | N20: =SUM(N6:N19) | P20: =SUM(P6:P19) | R20: =SUM(R6:R19) | T20: =SUM(T6:T19) | V20: =SUM(V6:V19) | X20: =SUM(X6:X19) | Z20: =SUM(Z6:Z19) | AB20: =SUM(AB6:AB19) | AD20: =SUM(AD6:AD19) | AF20: =SUM(AF6:AF19) | AH20: =SUM(AH6:AH19) | AJ20: =SUM(AJ6:AJ19) | AL20: =SUM(AL6:AL19)
A21: MARGE BRUTE CUMULEE | F21: =D20+F20 | H21: =F21+H20 | J21: =H21+J20 | L21: =J21+L20 | N21: =L21+N20 | P21: =N21+P20 | R21: =P21+R20 | T21: =R21+T20 | V21: =T21+V20 | X21: =V21+X20 | Z21: =X21+Z20 | AB21: =Z21+AB20 | AD21: =AB21+AD20 | AF21: =AD21+AF20 | AH21: =AF21+AH20 | AJ21: =AH21+AJ20 | AL21: =AJ21+AL20
A23: ATTENTION: Pensez à vérifier la saisonnalité de votre profession: ventes en été, reprise à la rentrée, hiver haut ou bas, effets des évenemnents type 'marroniers', etc.?

Sheet 3. test détail ventes réalisées
A1: Réalisé | B1: Nom : | C1: Oliver Van Droogenbroeck
C3: 46266 | E3: 46296 | G3: 46327 | I3: 46357 | K3: 46388 | M3: 46419 | O3: 46447 | Q3: 46478 | S3: 46508 | U3: 46539 | W3: 46569 | Y3: 46600 | AA3: 46631 | AC3: 46661 | AE3: 46692 | AG3: 46722 | AI3: 46753 | AK3: 46784
A4: TYPE DE PRESTATION | B4: Marge U | C4: 1 | E4: 2 | G4: 3 | I4: 4 | K4: 5 | M4: 6 | O4: 7 | Q4: 8 | S4: 9 | U4: 10 | W4: 11 | Y4: 12 | AA4: 13 | AC4: 14 | AE4: 15 | AG4: 16 | AI4: 17 | AK4: 18
B5: HTVA | C5: Nbre | D5: Tot. | E5: Nbre | F5: Tot. | G5: Nbre | H5: Tot. | I5: Nbre | J5: Tot. | K5: Nbre | L5: Tot. | M5: Nbre | N5: Tot. | O5: Nbre | P5: Tot. | Q5: Nbre | R5: Tot. | S5: Nbre | T5: Tot. | U5: Nbre | V5: Tot. | W5: Nbre | X5: Tot. | Y5: Nbre | Z5: Tot. | AA5: Nbre | AB5: Tot. | AC5: Nbre | AD5: Tot. | AE5: Nbre | AF5: Tot. | AG5: Nbre | AH5: Tot. | AI5: Nbre | AJ5: Tot. | AK5: Nbre | AL5: Tot.
A6: ='1. Calcul de Marge Brute'!A10 | B6: ='1. Calcul de Marge Brute'!K10 | D6: =C6*$B6 | F6: =E6*$B6 | H6: =G6*$B6 | J6: =I6*$B6 | L6: =K6*$B6 | N6: =M6*$B6 | P6: =O6*$B6 | R6: =Q6*$B6 | T6: =S6*$B6 | V6: =U6*$B6 | X6: =W6*$B6 | Z6: =Y6*$B6 | AB6: =AA6*$B6 | AD6: =AC6*$B6 | AF6: =AE6*$B6 | AH6: =AG6*$B6 | AJ6: =AI6*$B6 | AL6: =AK6*$B6
A7: ='1. Calcul de Marge Brute'!A11 | B7: ='1. Calcul de Marge Brute'!K11 | D7: =C7*$B7 | F7: =E7*$B7 | H7: =G7*$B7 | J7: =I7*$B7 | L7: =K7*$B7 | N7: =M7*$B7 | P7: =O7*$B7 | R7: =Q7*$B7 | T7: =S7*$B7 | V7: =U7*$B7 | X7: =W7*$B7 | Z7: =Y7*$B7 | AB7: =AA7*$B7 | AD7: =AC7*$B7 | AF7: =AE7*$B7 | AH7: =AG7*$B7 | AJ7: =AI7*$B7 | AL7: =AK7*$B7
A8: ='1. Calcul de Marge Brute'!A12 | B8: ='1. Calcul de Marge Brute'!K12 | D8: =C8*$B8 | F8: =E8*$B8 | H8: =G8*$B8 | J8: =I8*$B8 | L8: =K8*$B8 | N8: =M8*$B8 | P8: =O8*$B8 | R8: =Q8*$B8 | T8: =S8*$B8 | V8: =U8*$B8 | X8: =W8*$B8 | Z8: =Y8*$B8 | AB8: =AA8*$B8 | AD8: =AC8*$B8 | AF8: =AE8*$B8 | AH8: =AG8*$B8 | AJ8: =AI8*$B8 | AL8: =AK8*$B8
A9: ='1. Calcul de Marge Brute'!A13 | B9: ='1. Calcul de Marge Brute'!K13 | D9: =C9*$B9 | F9: =E9*$B9 | H9: =G9*$B9 | J9: =I9*$B9 | L9: =K9*$B9 | N9: =M9*$B9 | P9: =O9*$B9 | R9: =Q9*$B9 | T9: =S9*$B9 | V9: =U9*$B9 | X9: =W9*$B9 | Z9: =Y9*$B9 | AB9: =AA9*$B9 | AD9: =AC9*$B9 | AF9: =AE9*$B9 | AH9: =AG9*$B9 | AJ9: =AI9*$B9 | AL9: =AK9*$B9
A10: ='1. Calcul de Marge Brute'!A14 | B10: ='1. Calcul de Marge Brute'!K14 | D10: =C10*$B10 | F10: =E10*$B10 | H10: =G10*$B10 | J10: =I10*$B10 | L10: =K10*$B10 | N10: =M10*$B10 | P10: =O10*$B10 | R10: =Q10*$B10 | T10: =S10*$B10 | V10: =U10*$B10 | X10: =W10*$B10 | Z10: =Y10*$B10 | AB10: =AA10*$B10 | AD10: =AC10*$B10 | AF10: =AE10*$B10 | AH10: =AG10*$B10 | AJ10: =AI10*$B10 | AL10: =AK10*$B10
A11: ='1. Calcul de Marge Brute'!A15 | B11: ='1. Calcul de Marge Brute'!K15 | D11: =C11*$B11 | F11: =E11*$B11 | H11: =G11*$B11 | J11: =I11*$B11 | L11: =K11*$B11 | N11: =M11*$B11 | P11: =O11*$B11 | R11: =Q11*$B11 | T11: =S11*$B11 | V11: =U11*$B11 | X11: =W11*$B11 | Z11: =Y11*$B11 | AB11: =AA11*$B11 | AD11: =AC11*$B11 | AF11: =AE11*$B11 | AH11: =AG11*$B11 | AJ11: =AI11*$B11 | AL11: =AK11*$B11
A12: ='1. Calcul de Marge Brute'!A16 | B12: ='1. Calcul de Marge Brute'!K16 | D12: =C12*$B12 | F12: =E12*$B12 | H12: =G12*$B12 | J12: =I12*$B12 | L12: =K12*$B12 | N12: =M12*$B12 | P12: =O12*$B12 | R12: =Q12*$B12 | T12: =S12*$B12 | V12: =U12*$B12 | X12: =W12*$B12 | Z12: =Y12*$B12 | AB12: =AA12*$B12 | AD12: =AC12*$B12 | AF12: =AE12*$B12 | AH12: =AG12*$B12 | AJ12: =AI12*$B12 | AL12: =AK12*$B12
A13: ='1. Calcul de Marge Brute'!A17 | B13: ='1. Calcul de Marge Brute'!K17 | D13: =C13*$B13 | F13: =E13*$B13 | H13: =G13*$B13 | J13: =I13*$B13 | L13: =K13*$B13 | N13: =M13*$B13 | P13: =O13*$B13 | R13: =Q13*$B13 | T13: =S13*$B13 | V13: =U13*$B13 | X13: =W13*$B13 | Z13: =Y13*$B13 | AB13: =AA13*$B13 | AD13: =AC13*$B13 | AF13: =AE13*$B13 | AH13: =AG13*$B13 | AJ13: =AI13*$B13 | AL13: =AK13*$B13
A14: ='1. Calcul de Marge Brute'!A18 | B14: ='1. Calcul de Marge Brute'!K18 | D14: =C14*$B14 | F14: =E14*$B14 | H14: =G14*$B14 | J14: =I14*$B14 | L14: =K14*$B14 | N14: =M14*$B14 | P14: =O14*$B14 | R14: =Q14*$B14 | T14: =S14*$B14 | V14: =U14*$B14 | X14: =W14*$B14 | Z14: =Y14*$B14 | AB14: =AA14*$B14 | AD14: =AC14*$B14 | AF14: =AE14*$B14 | AH14: =AG14*$B14 | AJ14: =AI14*$B14 | AL14: =AK14*$B14
A15: ='1. Calcul de Marge Brute'!A19 | B15: ='1. Calcul de Marge Brute'!K19 | D15: =C15*$B15 | F15: =E15*$B15 | H15: =G15*$B15 | J15: =I15*$B15 | L15: =K15*$B15 | N15: =M15*$B15 | P15: =O15*$B15 | R15: =Q15*$B15 | T15: =S15*$B15 | V15: =U15*$B15 | X15: =W15*$B15 | Z15: =Y15*$B15 | AB15: =AA15*$B15 | AD15: =AC15*$B15 | AF15: =AE15*$B15 | AH15: =AG15*$B15 | AJ15: =AI15*$B15 | AL15: =AK15*$B15
A16: ='1. Calcul de Marge Brute'!A20 | B16: ='1. Calcul de Marge Brute'!K20 | D16: =C16*$B16 | F16: =E16*$B16 | H16: =G16*$B16 | J16: =I16*$B16 | L16: =K16*$B16 | N16: =M16*$B16 | P16: =O16*$B16 | R16: =Q16*$B16 | T16: =S16*$B16 | V16: =U16*$B16 | X16: =W16*$B16 | Z16: =Y16*$B16 | AB16: =AA16*$B16 | AD16: =AC16*$B16 | AF16: =AE16*$B16 | AH16: =AG16*$B16 | AJ16: =AI16*$B16 | AL16: =AK16*$B16
A17: ='1. Calcul de Marge Brute'!A21 | B17: ='1. Calcul de Marge Brute'!K21 | D17: =C17*$B17 | F17: =E17*$B17 | H17: =G17*$B17 | J17: =I17*$B17 | L17: =K17*$B17 | N17: =M17*$B17 | P17: =O17*$B17 | R17: =Q17*$B17 | T17: =S17*$B17 | V17: =U17*$B17 | X17: =W17*$B17 | Z17: =Y17*$B17 | AB17: =AA17*$B17 | AD17: =AC17*$B17 | AF17: =AE17*$B17 | AH17: =AG17*$B17 | AJ17: =AI17*$B17 | AL17: =AK17*$B17
A18: ='1. Calcul de Marge Brute'!A22 | B18: ='1. Calcul de Marge Brute'!K22 | D18: =C18*$B18 | F18: =E18*$B18 | H18: =G18*$B18 | J18: =I18*$B18 | L18: =K18*$B18 | N18: =M18*$B18 | P18: =O18*$B18 | R18: =Q18*$B18 | T18: =S18*$B18 | V18: =U18*$B18 | X18: =W18*$B18 | Z18: =Y18*$B18 | AB18: =AA18*$B18 | AD18: =AC18*$B18 | AF18: =AE18*$B18 | AH18: =AG18*$B18 | AJ18: =AI18*$B18 | AL18: =AK18*$B18
A20: TOTAUX | D20: =SUM(D6:D19) | F20: =SUM(F6:F19) | H20: =SUM(H6:H19) | J20: =SUM(J6:J19) | L20: =SUM(L6:L19) | N20: =SUM(N6:N19) | P20: =SUM(P6:P19) | R20: =SUM(R6:R19) | T20: =SUM(T6:T19) | V20: =SUM(V6:V19) | X20: =SUM(X6:X19) | Z20: =SUM(Z6:Z19) | AB20: =SUM(AB6:AB19) | AD20: =SUM(AD6:AD19) | AF20: =SUM(AF6:AF19) | AH20: =SUM(AH6:AH19) | AJ20: =SUM(AJ6:AJ19) | AL20: =SUM(AL6:AL19)
A21: MARGE BRUTE CUMULEE | F21: =D20+F20 | H21: =F21+H20 | J21: =H21+J20 | L21: =J21+L20 | N21: =L21+N20 | P21: =N21+P20 | R21: =P21+R20 | T21: =R21+T20 | V21: =T21+V20 | X21: =V21+X20 | Z21: =X21+Z20 | AB21: =Z21+AB20 | AD21: =AB21+AD20 | AF21: =AD21+AF20 | AH21: =AF21+AH20 | AJ21: =AH21+AJ20 | AL21: =AJ21+AL20
A23: Vous reporterez ici les chiffres réellement atteint pendant votre test.

Sheet 4. Vue globale  MB mensuels 
A1: Nom : | C1: Oliver Van Droogenbroeck
B2: Ma marge brute mensuelle
H4: Test grandeur nature | Z4: Autonomie
B7: 1/ | C7: Mes objectifs mensuels | H7: ='2. Détail prévisionnel ventes '!D20 | I7: ='2. Détail prévisionnel ventes '!F20 | J7: ='2. Détail prévisionnel ventes '!H20 | K7: ='2. Détail prévisionnel ventes '!J20 | L7: ='2. Détail prévisionnel ventes '!L20 | M7: ='2. Détail prévisionnel ventes '!N20 | N7: ='2. Détail prévisionnel ventes '!P20 | O7: ='2. Détail prévisionnel ventes '!R20 | P7: ='2. Détail prévisionnel ventes '!T20 | Q7: ='2. Détail prévisionnel ventes '!V20 | R7: ='2. Détail prévisionnel ventes '!X20 | S7: ='2. Détail prévisionnel ventes '!Z20 | T7: ='2. Détail prévisionnel ventes '!AB20 | U7: ='2. Détail prévisionnel ventes '!AD20 | V7: ='2. Détail prévisionnel ventes '!AF20 | W7: ='2. Détail prévisionnel ventes '!AH20 | X7: ='2. Détail prévisionnel ventes '!AJ20 | Y7: ='2. Détail prévisionnel ventes '!AL20
B8: 2/ | C8: Le parcours "moyen" mensuel | H8: 0 | I8: 0 | J8: 600 | K8: 900 | L8: 1000 | M8: 1100 | N8: 1300 | O8: 1400 | P8: 1500 | Q8: 1600 | R8: 1700 | S8: 1800 | T8: 1900 | U8: 2000 | V8: 2100 | W8: 2200 | X8: 2300 | Y8: 2400
B9: 3/ | C9: Mes résultats mensuels | H9: ='3. test détail ventes réalisées'!D20 | I9: ='3. test détail ventes réalisées'!F20 | J9: ='3. test détail ventes réalisées'!H20 | K9: ='3. test détail ventes réalisées'!J20 | L9: ='3. test détail ventes réalisées'!L20 | M9: ='3. test détail ventes réalisées'!N20 | N9: ='3. test détail ventes réalisées'!P20 | O9: ='3. test détail ventes réalisées'!R20 | P9: ='3. test détail ventes réalisées'!T20 | Q9: ='3. test détail ventes réalisées'!V20 | R9: ='3. test détail ventes réalisées'!X20 | S9: ='3. test détail ventes réalisées'!Z20 | T9: ='3. test détail ventes réalisées'!AB20 | U9: ='3. test détail ventes réalisées'!AD20 | V9: ='3. test détail ventes réalisées'!AF20 | W9: ='3. test détail ventes réalisées'!AH20 | X9: ='3. test détail ventes réalisées'!AJ20 | Y9: ='3. test détail ventes réalisées'!AL20
H10: 1 | I10: =H10+1 | J10: =I10+1 | K10: =J10+1 | L10: =K10+1 | M10: =L10+1 | N10: =M10+1 | O10: =N10+1 | P10: =O10+1 | ... Y10: =X10+1 | Z10: 1 | AA10: =Z10+1 | AB10: =AA10+1 | AC10: =AB10+1 | AD10: =AC10+1 | AE10: =AD10+1
H11: Vendre - produire - facturer | Z11: Lancement seul
H14: 1 | I14: =H14+1 | J14: =I14+1 | K14: =J14+1 | L14: =K14+1 | M14: =L14+1 | N14: =M14+1 | O14: =N14+1 | P14: =O14+1 | ... Y14: =X14+1
B15: 4/ | C15: Mes objectifs cumulés | I15: =+H7 | J15: =+I15+I7 | K15: =+J15+J7 | L15: =+K15+K7 | M15: =+L15+L7 | N15: =+M15+M7 | O15: =+N15+N7 | P15: =+O15+O7 | Q15: =+P15+P7 | ... Z15: =+Y15+Y7
B16: 5/ | C16: Le parcours "moyen" cumulé | I16: =+H8 | J16: =+I16+I8 | K16: =+J16+J8 | L16: =+K16+K8 | M16: =+L16+L8 | N16: =+M16+M8 | O16: =+N16+N8 | P16: =+O16+O8 | Q16: =+P16+P8 | ... Z16: =+Y16+Y8
B17: 6/ | C17: Mes résultats cumulés | I17: =+H9 | J17: =+I17+I9 | K17: =+J17+J9 | L17: =+K17+K9 | M17: =+L17+L9 | N17: =+M17+M9 | O17: =+N17+N9 | P17: =+O17+O9 | Q17: =+P17+P9 | ... W17: =+V17+V9

Sheet Feuil1

Sheet Feuil2
